[{"key":"21","display":"Barrier","internal":"SummonerBarrier"},{"key":"1","display":"Cleanse","internal":"SummonerBoost"},{"key":"35","display":"Disabled Summoner Spells","internal":"SummonerDarkStarChampSelect1"},{"key":"36","display":"Disabled Summoner Spells","internal":"SummonerDarkStarChampSelect2"},{"key":"14","display":"Ignite","internal":"SummonerDot"},{"key":"3","display":"Exhaust","internal":"SummonerExhaust"},{"key":"4","display":"Flash","internal":"SummonerFlash"},{"key":"6","display":"Ghost","internal":"SummonerHaste"},{"key":"7","display":"Heal","internal":"SummonerHeal"},{"key":"13","display":"Clarity","internal":"SummonerMana"},{"key":"52","display":"Warp","internal":"SummonerOdysseyFlash"},{"key":"51","display":"Ghost","internal":"SummonerOdysseyGhost"},{"key":"50","display":"Resuscitate","internal":"SummonerOdysseyRevive"},{"key":"30","display":"To the King!","internal":"SummonerPoroRecall"},{"key":"31","display":"Poro Toss","internal":"SummonerPoroThrow"},{"key":"33","display":"Nexus Siege: Siege Weapon Slot","internal":"SummonerSiegeChampSelect1"},{"key":"34","display":"Nexus Siege: Siege Weapon Slot","internal":"SummonerSiegeChampSelect2"},{"key":"11","display":"Smite","internal":"SummonerSmite"},{"key":"39","display":"Ultra (Rapidly Flung) Mark","internal":"SummonerSnowURFSnowball_Mark"},{"key":"32","display":"Mark","internal":"SummonerSnowball"},{"key":"12","display":"Teleport","internal":"SummonerTeleport"}]